{
  "latest_release": {
    "version": "v0.4.1",
    "name": "Latest Release",
    "published_at": "2025-11-28T00:31:10.966407",
    "html_url": "https://github.com/PipFoweraker/pdoom1/releases",
    "body": "Latest development version"
  },
  "repository_stats": {
    "stars": 0,
    "forks": 0,
    "open_issues": 0,
    "last_updated": "2025-11-28T00:31:11.050256"
  },
  "last_updated": "2025-11-28T00:31:11.107718",
  "game_stats": {
    "baseline_doom_percent": 23,
    "frontier_labs_count": 5,
    "strategic_possibilities": 10000,
    "last_calculated": "2025-11-28T00:31:11.107710"
  }
}