{
  "meta": {
    "week_id": "2026_W22",
    "season": "2025_Q4",
    "generated": "2026-05-31T23:23:26.505526Z",
    "game_version": "v0.4.1",
    "competition_type": "weekly_league",
    "start_date": "2026-05-25T00:00:00",
    "end_date": "2026-05-31T23:59:59",
    "total_participants": 0,
    "total_submissions": 0
  },
  "seed": "weekly_2026_W22_7a099351",
  "economic_model": "Bootstrap_v0.4.1",
  "week_info": {
    "week_id": "2026_W22",
    "year": 2026,
    "week_number": 22,
    "start_date": "2026-05-25",
    "end_date": "2026-05-31",
    "start_timestamp": "2026-05-25T00:00:00",
    "end_timestamp": "2026-05-31T23:59:59",
    "days_remaining": 0,
    "hours_remaining": 0,
    "is_current": true,
    "season": "2025_Q4"
  },
  "entries": [],
  "statistics": {
    "highest_score": 0,
    "average_score": 0.0,
    "total_games": 0,
    "unique_players": 0
  },
  "archived_at": "2026-06-07T14:32:44.123156Z",
  "archive_status": "completed"
}